{
    "data": [
        {
            "heading": "0328-HTML",
            "content": [
                {
                    "path": "0328-1 第一个网页.html",
                    "title": "第一个网页"
                },
                {
                    "path": "0328-2.html",
                    "title": "第二个网页"
                },
                {
                    "path": "0328-3 标题和段落.html",
                    "title": "标题和段落"
                },
                {
                    "path": "0328-4.html",
                    "title": "标签"
                }
            ]
        },
        {
            "heading": "0329-HTML",
            "content": [
                {
                    "path": "0329-1 文字强调和图片.html",
                    "title": "文字强调和图片"
                },
                {
                    "path": "0329-2.html",
                    "title": "标签(a,em,strong,img)"
                }
            ]
        },
        {
            "heading": "0330-HTML",
            "content": [
                {
                    "path": "0330-1 表格和列表标签.html",
                    "title": "表格和列表标签1"
                },
                {
                    "path": "0330-2.html",
                    "title": "表格和列表标签2"
                },
                {
                    "path": "0330-3.html",
                    "title": "表格和列表标签3"
                },
                {
                    "path": "0330-4.html",
                    "title": "表格和列表标签4"
                },
                {
                    "path": "0330-5 表单元素.html",
                    "title": "表单元素"
                },
                {
                    "path": "0330-6.html",
                    "title": "form表单"
                },
                {
                    "path": "0330-7框架.html",
                    "title": "frame框架"
                }
            ]
        }
    ],
    "result":true
}